setup.cfg
setup.py
http/__init__.py
pyhttpclient.egg-info/PKG-INFO
pyhttpclient.egg-info/SOURCES.txt
pyhttpclient.egg-info/dependency_links.txt
pyhttpclient.egg-info/top_level.txt