Metadata-Version: 1.1
Name: pyhttpclient
Version: 0.1.2
Summary: Python helper of http request
Home-page: https://github.com/sillyemperor/http
Author: Wang Jiang
Author-email: sillyemperor@163.com
License: MIT
Keywords: http get post
Platform: UNKNOWN
Classifier: Development Status :: 5 - Production/Stable
Classifier: Intended Audience :: Developers
Classifier: Topic :: Software Development :: Libraries
Classifier: License :: OSI Approved :: MIT License
Classifier: Programming Language :: Python :: 2
Classifier: Programming Language :: Python :: 2.7
